{
  "subject_key": "골프존",
  "subject_name": "골프존",
  "latest_report_date": "2026-05-06",
  "report_count": 2,
  "active_broker_count": 2,
  "active_brokers": [
    "신한투자증권",
    "유진투자증권"
  ],
  "change_summary": {
    "changed_reports": 2,
    "target_price_up": 0,
    "target_price_down": 0,
    "opinion_changed": 0,
    "opinion_up": 0,
    "opinion_down": 0,
    "analyst_changed": 0,
    "coverage_initiated": 2
  },
  "target_summary": {
    "count": 2,
    "high": 73000,
    "low": 70000,
    "avg": 71500
  },
  "opinion_summary": [
    {
      "label": "buy",
      "count": 2
    }
  ],
  "charts": {
    "target_price_history": [
      {
        "date": "2026-04-24",
        "broker": "신한투자증권",
        "title": "골프존 - 해외시장, 해법이 되다",
        "ticker": null,
        "detail_url": "https://finance.naver.com/research/company_read.naver?nid=91851&page=3",
        "pdf_url": null,
        "primary_url": "https://finance.naver.com/research/company_read.naver?nid=91851&page=3",
        "target_price": "73,000",
        "target_price_value": 73000,
        "opinion": "매수",
        "opinion_normalized": "buy",
        "score": 7.9,
        "has_change_signal": true
      },
      {
        "date": "2026-05-06",
        "broker": "유진투자증권",
        "title": "골프존 - 1Q26P Review: 6분기 연속 해외 매출 증가",
        "ticker": null,
        "detail_url": "https://finance.naver.com/research/company_read.naver?nid=92465&page=2",
        "pdf_url": "https://stock.pstatic.net/stock-research/company/63/20260506_company_222333000.pdf",
        "primary_url": "https://stock.pstatic.net/stock-research/company/63/20260506_company_222333000.pdf",
        "target_price": "70,000",
        "target_price_value": 70000,
        "opinion": "Buy",
        "opinion_normalized": "buy",
        "score": 7.45,
        "has_change_signal": true
      }
    ],
    "opinion_distribution": [
      {
        "label": "buy",
        "count": 2
      }
    ],
    "broker_timeline": [
      {
        "date": "2026-04-24",
        "broker": "신한투자증권",
        "title": "골프존 - 해외시장, 해법이 되다",
        "ticker": null,
        "detail_url": "https://finance.naver.com/research/company_read.naver?nid=91851&page=3",
        "pdf_url": null,
        "primary_url": "https://finance.naver.com/research/company_read.naver?nid=91851&page=3",
        "target_price": "73,000",
        "target_price_value": 73000,
        "opinion": "매수",
        "opinion_normalized": "buy",
        "score": 7.9,
        "has_change_signal": true
      },
      {
        "date": "2026-05-06",
        "broker": "유진투자증권",
        "title": "골프존 - 1Q26P Review: 6분기 연속 해외 매출 증가",
        "ticker": null,
        "detail_url": "https://finance.naver.com/research/company_read.naver?nid=92465&page=2",
        "pdf_url": "https://stock.pstatic.net/stock-research/company/63/20260506_company_222333000.pdf",
        "primary_url": "https://stock.pstatic.net/stock-research/company/63/20260506_company_222333000.pdf",
        "target_price": "70,000",
        "target_price_value": 70000,
        "opinion": "Buy",
        "opinion_normalized": "buy",
        "score": 7.45,
        "has_change_signal": true
      }
    ],
    "window_days": 14
  },
  "target_price_history": [
    {
      "date": "2026-04-24",
      "broker": "신한투자증권",
      "title": "골프존 - 해외시장, 해법이 되다",
      "ticker": null,
      "detail_url": "https://finance.naver.com/research/company_read.naver?nid=91851&page=3",
      "pdf_url": null,
      "primary_url": "https://finance.naver.com/research/company_read.naver?nid=91851&page=3",
      "target_price": "73,000",
      "target_price_value": 73000,
      "opinion": "매수",
      "opinion_normalized": "buy",
      "score": 7.9,
      "has_change_signal": true
    },
    {
      "date": "2026-05-06",
      "broker": "유진투자증권",
      "title": "골프존 - 1Q26P Review: 6분기 연속 해외 매출 증가",
      "ticker": null,
      "detail_url": "https://finance.naver.com/research/company_read.naver?nid=92465&page=2",
      "pdf_url": "https://stock.pstatic.net/stock-research/company/63/20260506_company_222333000.pdf",
      "primary_url": "https://stock.pstatic.net/stock-research/company/63/20260506_company_222333000.pdf",
      "target_price": "70,000",
      "target_price_value": 70000,
      "opinion": "Buy",
      "opinion_normalized": "buy",
      "score": 7.45,
      "has_change_signal": true
    }
  ],
  "opinion_distribution": [
    {
      "label": "buy",
      "count": 2
    }
  ],
  "broker_timeline": [
    {
      "date": "2026-04-24",
      "broker": "신한투자증권",
      "title": "골프존 - 해외시장, 해법이 되다",
      "ticker": null,
      "detail_url": "https://finance.naver.com/research/company_read.naver?nid=91851&page=3",
      "pdf_url": null,
      "primary_url": "https://finance.naver.com/research/company_read.naver?nid=91851&page=3",
      "target_price": "73,000",
      "target_price_value": 73000,
      "opinion": "매수",
      "opinion_normalized": "buy",
      "score": 7.9,
      "has_change_signal": true
    },
    {
      "date": "2026-05-06",
      "broker": "유진투자증권",
      "title": "골프존 - 1Q26P Review: 6분기 연속 해외 매출 증가",
      "ticker": null,
      "detail_url": "https://finance.naver.com/research/company_read.naver?nid=92465&page=2",
      "pdf_url": "https://stock.pstatic.net/stock-research/company/63/20260506_company_222333000.pdf",
      "primary_url": "https://stock.pstatic.net/stock-research/company/63/20260506_company_222333000.pdf",
      "target_price": "70,000",
      "target_price_value": 70000,
      "opinion": "Buy",
      "opinion_normalized": "buy",
      "score": 7.45,
      "has_change_signal": true
    }
  ],
  "broker_summary": [
    {
      "name": "유진투자증권",
      "count": 1
    },
    {
      "name": "신한투자증권",
      "count": 1
    }
  ],
  "category_summary": [
    {
      "label": "종목분석",
      "count": 2
    }
  ],
  "latest_by_broker": [
    {
      "source": "naver_research",
      "category": "company",
      "category_label": "종목분석",
      "report_id": "92465",
      "title": "1Q26P Review: 6분기 연속 해외 매출 증가",
      "display_title": "골프존 - 1Q26P Review: 6분기 연속 해외 매출 증가",
      "broker": "유진투자증권",
      "published_date": "2026-05-06",
      "detail_url": "https://finance.naver.com/research/company_read.naver?nid=92465&page=2",
      "pdf_url": "https://stock.pstatic.net/stock-research/company/63/20260506_company_222333000.pdf",
      "subject": "골프존",
      "subject_key": "골프존",
      "views": 1475,
      "analyst": null,
      "target_price": "70,000",
      "target_price_value": 70000,
      "opinion": "Buy",
      "opinion_normalized": "buy",
      "has_pdf_text": false,
      "content_sources": [
        "html"
      ],
      "excerpt": "\" 1Q26P Review: 실적 부진속에 해외 사업은 5분기 연속 성장세 지속. 최근(04/30) 발표한 2026년 1분기 잠정실적(연결 기준)은 매출액 1,118억원, 영업이익 141억원으로 전년동기 대비 각각 13.9%, 47.4% 감소함.",
      "summary": "\" 1Q26P Review: 실적 부진속에 해외 사업은 5분기 연속 성장세 지속. 최근(04/30) 발표한 2026년 1분기 잠정실적(연결 기준)은 매출액 1,118억원, 영업이익 141억원으로 전년동기 대비 각각 13.9%, 47.4% 감소함. 시장 컨센서스(매출액 1,199억원, 영업이익 212억원) 대비 매출액은 유사한 수준이었으나, 영업이익은 큰 폭으로 하회함.",
      "summary_engine": "rule",
      "investment_memo": {},
      "score": 7.45,
      "score_reasons": [
        "종목분석 카테고리",
        "조회수 상위권",
        "목표가 포함",
        "투자의견 포함"
      ],
      "priority_subject_matches": [],
      "priority_keyword_matches": [],
      "is_priority_match": false,
      "previous_report_date": null,
      "previous_target_price": null,
      "previous_opinion": null,
      "previous_analyst": null,
      "target_price_change": null,
      "target_price_change_pct": null,
      "opinion_changed": false,
      "opinion_change_direction": null,
      "analyst_changed": false,
      "coverage_initiated": true,
      "change_types": [
        "coverage_initiated"
      ],
      "change_reasons": [
        "신규 커버리지"
      ],
      "has_change_signal": true,
      "ticker": null
    },
    {
      "source": "naver_research",
      "category": "company",
      "category_label": "종목분석",
      "report_id": "91851",
      "title": "해외시장, 해법이 되다",
      "display_title": "골프존 - 해외시장, 해법이 되다",
      "broker": "신한투자증권",
      "published_date": "2026-04-24",
      "detail_url": "https://finance.naver.com/research/company_read.naver?nid=91851&page=3",
      "pdf_url": null,
      "subject": "골프존",
      "subject_key": "골프존",
      "views": 560,
      "analyst": null,
      "target_price": "73,000",
      "target_price_value": 73000,
      "opinion": "매수",
      "opinion_normalized": "buy",
      "has_pdf_text": false,
      "content_sources": [
        "html"
      ],
      "excerpt": "국내 상저하고, 해외 성장세 유효 하반기 역성장 기조 전환, 2026년 실적은 뚜렷한 상저하고 예상.",
      "summary": "국내 상저하고, 해외 성장세 유효 하반기 역성장 기조 전환, 2026년 실적은 뚜렷한 상저하고 예상. 미국 골프 시뮬레이터 시장 성장세와 일본 시장 매출 정체 해소 시 주가의 의미있는 반등세 전망.",
      "summary_engine": "rule",
      "score": 7.9,
      "score_reasons": [
        "종목분석 카테고리",
        "목표가 포함",
        "투자의견 포함",
        "우선 추적 증권사"
      ],
      "priority_subject_matches": [],
      "priority_keyword_matches": [],
      "is_priority_match": false,
      "previous_report_date": null,
      "previous_target_price": null,
      "previous_opinion": null,
      "previous_analyst": null,
      "target_price_change": null,
      "target_price_change_pct": null,
      "opinion_changed": false,
      "opinion_change_direction": null,
      "analyst_changed": false,
      "coverage_initiated": true,
      "change_types": [
        "coverage_initiated"
      ],
      "change_reasons": [
        "신규 커버리지"
      ],
      "has_change_signal": true,
      "ticker": null
    }
  ],
  "recent_changes": [
    {
      "source": "naver_research",
      "category": "company",
      "category_label": "종목분석",
      "report_id": "92465",
      "title": "1Q26P Review: 6분기 연속 해외 매출 증가",
      "display_title": "골프존 - 1Q26P Review: 6분기 연속 해외 매출 증가",
      "broker": "유진투자증권",
      "published_date": "2026-05-06",
      "detail_url": "https://finance.naver.com/research/company_read.naver?nid=92465&page=2",
      "pdf_url": "https://stock.pstatic.net/stock-research/company/63/20260506_company_222333000.pdf",
      "subject": "골프존",
      "subject_key": "골프존",
      "views": 1475,
      "analyst": null,
      "target_price": "70,000",
      "target_price_value": 70000,
      "opinion": "Buy",
      "opinion_normalized": "buy",
      "has_pdf_text": false,
      "content_sources": [
        "html"
      ],
      "excerpt": "\" 1Q26P Review: 실적 부진속에 해외 사업은 5분기 연속 성장세 지속. 최근(04/30) 발표한 2026년 1분기 잠정실적(연결 기준)은 매출액 1,118억원, 영업이익 141억원으로 전년동기 대비 각각 13.9%, 47.4% 감소함.",
      "summary": "\" 1Q26P Review: 실적 부진속에 해외 사업은 5분기 연속 성장세 지속. 최근(04/30) 발표한 2026년 1분기 잠정실적(연결 기준)은 매출액 1,118억원, 영업이익 141억원으로 전년동기 대비 각각 13.9%, 47.4% 감소함. 시장 컨센서스(매출액 1,199억원, 영업이익 212억원) 대비 매출액은 유사한 수준이었으나, 영업이익은 큰 폭으로 하회함.",
      "summary_engine": "rule",
      "investment_memo": {},
      "score": 7.45,
      "score_reasons": [
        "종목분석 카테고리",
        "조회수 상위권",
        "목표가 포함",
        "투자의견 포함"
      ],
      "priority_subject_matches": [],
      "priority_keyword_matches": [],
      "is_priority_match": false,
      "previous_report_date": null,
      "previous_target_price": null,
      "previous_opinion": null,
      "previous_analyst": null,
      "target_price_change": null,
      "target_price_change_pct": null,
      "opinion_changed": false,
      "opinion_change_direction": null,
      "analyst_changed": false,
      "coverage_initiated": true,
      "change_types": [
        "coverage_initiated"
      ],
      "change_reasons": [
        "신규 커버리지"
      ],
      "has_change_signal": true,
      "ticker": null
    },
    {
      "source": "naver_research",
      "category": "company",
      "category_label": "종목분석",
      "report_id": "91851",
      "title": "해외시장, 해법이 되다",
      "display_title": "골프존 - 해외시장, 해법이 되다",
      "broker": "신한투자증권",
      "published_date": "2026-04-24",
      "detail_url": "https://finance.naver.com/research/company_read.naver?nid=91851&page=3",
      "pdf_url": null,
      "subject": "골프존",
      "subject_key": "골프존",
      "views": 560,
      "analyst": null,
      "target_price": "73,000",
      "target_price_value": 73000,
      "opinion": "매수",
      "opinion_normalized": "buy",
      "has_pdf_text": false,
      "content_sources": [
        "html"
      ],
      "excerpt": "국내 상저하고, 해외 성장세 유효 하반기 역성장 기조 전환, 2026년 실적은 뚜렷한 상저하고 예상.",
      "summary": "국내 상저하고, 해외 성장세 유효 하반기 역성장 기조 전환, 2026년 실적은 뚜렷한 상저하고 예상. 미국 골프 시뮬레이터 시장 성장세와 일본 시장 매출 정체 해소 시 주가의 의미있는 반등세 전망.",
      "summary_engine": "rule",
      "score": 7.9,
      "score_reasons": [
        "종목분석 카테고리",
        "목표가 포함",
        "투자의견 포함",
        "우선 추적 증권사"
      ],
      "priority_subject_matches": [],
      "priority_keyword_matches": [],
      "is_priority_match": false,
      "previous_report_date": null,
      "previous_target_price": null,
      "previous_opinion": null,
      "previous_analyst": null,
      "target_price_change": null,
      "target_price_change_pct": null,
      "opinion_changed": false,
      "opinion_change_direction": null,
      "analyst_changed": false,
      "coverage_initiated": true,
      "change_types": [
        "coverage_initiated"
      ],
      "change_reasons": [
        "신규 커버리지"
      ],
      "has_change_signal": true,
      "ticker": null
    }
  ],
  "timeline": [
    {
      "source": "naver_research",
      "category": "company",
      "category_label": "종목분석",
      "report_id": "92465",
      "title": "1Q26P Review: 6분기 연속 해외 매출 증가",
      "display_title": "골프존 - 1Q26P Review: 6분기 연속 해외 매출 증가",
      "broker": "유진투자증권",
      "published_date": "2026-05-06",
      "detail_url": "https://finance.naver.com/research/company_read.naver?nid=92465&page=2",
      "pdf_url": "https://stock.pstatic.net/stock-research/company/63/20260506_company_222333000.pdf",
      "subject": "골프존",
      "subject_key": "골프존",
      "views": 1475,
      "analyst": null,
      "target_price": "70,000",
      "target_price_value": 70000,
      "opinion": "Buy",
      "opinion_normalized": "buy",
      "has_pdf_text": false,
      "content_sources": [
        "html"
      ],
      "excerpt": "\" 1Q26P Review: 실적 부진속에 해외 사업은 5분기 연속 성장세 지속. 최근(04/30) 발표한 2026년 1분기 잠정실적(연결 기준)은 매출액 1,118억원, 영업이익 141억원으로 전년동기 대비 각각 13.9%, 47.4% 감소함.",
      "summary": "\" 1Q26P Review: 실적 부진속에 해외 사업은 5분기 연속 성장세 지속. 최근(04/30) 발표한 2026년 1분기 잠정실적(연결 기준)은 매출액 1,118억원, 영업이익 141억원으로 전년동기 대비 각각 13.9%, 47.4% 감소함. 시장 컨센서스(매출액 1,199억원, 영업이익 212억원) 대비 매출액은 유사한 수준이었으나, 영업이익은 큰 폭으로 하회함.",
      "summary_engine": "rule",
      "investment_memo": {},
      "score": 7.45,
      "score_reasons": [
        "종목분석 카테고리",
        "조회수 상위권",
        "목표가 포함",
        "투자의견 포함"
      ],
      "priority_subject_matches": [],
      "priority_keyword_matches": [],
      "is_priority_match": false,
      "previous_report_date": null,
      "previous_target_price": null,
      "previous_opinion": null,
      "previous_analyst": null,
      "target_price_change": null,
      "target_price_change_pct": null,
      "opinion_changed": false,
      "opinion_change_direction": null,
      "analyst_changed": false,
      "coverage_initiated": true,
      "change_types": [
        "coverage_initiated"
      ],
      "change_reasons": [
        "신규 커버리지"
      ],
      "has_change_signal": true,
      "ticker": null
    },
    {
      "source": "naver_research",
      "category": "company",
      "category_label": "종목분석",
      "report_id": "91851",
      "title": "해외시장, 해법이 되다",
      "display_title": "골프존 - 해외시장, 해법이 되다",
      "broker": "신한투자증권",
      "published_date": "2026-04-24",
      "detail_url": "https://finance.naver.com/research/company_read.naver?nid=91851&page=3",
      "pdf_url": null,
      "subject": "골프존",
      "subject_key": "골프존",
      "views": 560,
      "analyst": null,
      "target_price": "73,000",
      "target_price_value": 73000,
      "opinion": "매수",
      "opinion_normalized": "buy",
      "has_pdf_text": false,
      "content_sources": [
        "html"
      ],
      "excerpt": "국내 상저하고, 해외 성장세 유효 하반기 역성장 기조 전환, 2026년 실적은 뚜렷한 상저하고 예상.",
      "summary": "국내 상저하고, 해외 성장세 유효 하반기 역성장 기조 전환, 2026년 실적은 뚜렷한 상저하고 예상. 미국 골프 시뮬레이터 시장 성장세와 일본 시장 매출 정체 해소 시 주가의 의미있는 반등세 전망.",
      "summary_engine": "rule",
      "score": 7.9,
      "score_reasons": [
        "종목분석 카테고리",
        "목표가 포함",
        "투자의견 포함",
        "우선 추적 증권사"
      ],
      "priority_subject_matches": [],
      "priority_keyword_matches": [],
      "is_priority_match": false,
      "previous_report_date": null,
      "previous_target_price": null,
      "previous_opinion": null,
      "previous_analyst": null,
      "target_price_change": null,
      "target_price_change_pct": null,
      "opinion_changed": false,
      "opinion_change_direction": null,
      "analyst_changed": false,
      "coverage_initiated": true,
      "change_types": [
        "coverage_initiated"
      ],
      "change_reasons": [
        "신규 커버리지"
      ],
      "has_change_signal": true,
      "ticker": null
    }
  ]
}