{
  "subject_key": "케이엠더블유",
  "subject_name": "케이엠더블유",
  "latest_report_date": "2026-05-19",
  "report_count": 1,
  "active_broker_count": 1,
  "active_brokers": [
    "하나증권"
  ],
  "change_summary": {
    "changed_reports": 1,
    "target_price_up": 0,
    "target_price_down": 0,
    "opinion_changed": 0,
    "opinion_up": 0,
    "opinion_down": 0,
    "analyst_changed": 0,
    "coverage_initiated": 1
  },
  "target_summary": {
    "count": 1,
    "high": 70000,
    "low": 70000,
    "avg": 70000
  },
  "opinion_summary": [
    {
      "label": "buy",
      "count": 1
    }
  ],
  "charts": {
    "target_price_history": [
      {
        "date": "2026-05-19",
        "broker": "하나증권",
        "title": "케이엠더블유 - 중요한 건 올해가 아닌 내년도 실적입니다",
        "ticker": "032500",
        "detail_url": "https://finance.naver.com/research/company_read.naver?nid=93145&page=1",
        "pdf_url": "https://stock.pstatic.net/stock-research/company/57/20260519_company_123293000.pdf",
        "primary_url": "https://stock.pstatic.net/stock-research/company/57/20260519_company_123293000.pdf",
        "target_price": "70,000",
        "target_price_value": 70000,
        "opinion": "Buy",
        "opinion_normalized": "buy",
        "score": 12.95,
        "has_change_signal": true
      }
    ],
    "opinion_distribution": [
      {
        "label": "buy",
        "count": 1
      }
    ],
    "broker_timeline": [
      {
        "date": "2026-05-19",
        "broker": "하나증권",
        "title": "케이엠더블유 - 중요한 건 올해가 아닌 내년도 실적입니다",
        "ticker": "032500",
        "detail_url": "https://finance.naver.com/research/company_read.naver?nid=93145&page=1",
        "pdf_url": "https://stock.pstatic.net/stock-research/company/57/20260519_company_123293000.pdf",
        "primary_url": "https://stock.pstatic.net/stock-research/company/57/20260519_company_123293000.pdf",
        "target_price": "70,000",
        "target_price_value": 70000,
        "opinion": "Buy",
        "opinion_normalized": "buy",
        "score": 12.95,
        "has_change_signal": true
      }
    ],
    "window_days": 14
  },
  "target_price_history": [
    {
      "date": "2026-05-19",
      "broker": "하나증권",
      "title": "케이엠더블유 - 중요한 건 올해가 아닌 내년도 실적입니다",
      "ticker": "032500",
      "detail_url": "https://finance.naver.com/research/company_read.naver?nid=93145&page=1",
      "pdf_url": "https://stock.pstatic.net/stock-research/company/57/20260519_company_123293000.pdf",
      "primary_url": "https://stock.pstatic.net/stock-research/company/57/20260519_company_123293000.pdf",
      "target_price": "70,000",
      "target_price_value": 70000,
      "opinion": "Buy",
      "opinion_normalized": "buy",
      "score": 12.95,
      "has_change_signal": true
    }
  ],
  "opinion_distribution": [
    {
      "label": "buy",
      "count": 1
    }
  ],
  "broker_timeline": [
    {
      "date": "2026-05-19",
      "broker": "하나증권",
      "title": "케이엠더블유 - 중요한 건 올해가 아닌 내년도 실적입니다",
      "ticker": "032500",
      "detail_url": "https://finance.naver.com/research/company_read.naver?nid=93145&page=1",
      "pdf_url": "https://stock.pstatic.net/stock-research/company/57/20260519_company_123293000.pdf",
      "primary_url": "https://stock.pstatic.net/stock-research/company/57/20260519_company_123293000.pdf",
      "target_price": "70,000",
      "target_price_value": 70000,
      "opinion": "Buy",
      "opinion_normalized": "buy",
      "score": 12.95,
      "has_change_signal": true
    }
  ],
  "broker_summary": [
    {
      "name": "하나증권",
      "count": 1
    }
  ],
  "category_summary": [
    {
      "label": "종목분석",
      "count": 1
    }
  ],
  "latest_by_broker": [
    {
      "source": "naver_research",
      "category": "company",
      "category_label": "종목분석",
      "report_id": "93145",
      "title": "중요한 건 올해가 아닌 내년도 실적입니다",
      "display_title": "케이엠더블유 - 중요한 건 올해가 아닌 내년도 실적입니다",
      "broker": "하나증권",
      "published_date": "2026-05-19",
      "detail_url": "https://finance.naver.com/research/company_read.naver?nid=93145&page=1",
      "pdf_url": "https://stock.pstatic.net/stock-research/company/57/20260519_company_123293000.pdf",
      "primary_url": "https://stock.pstatic.net/stock-research/company/57/20260519_company_123293000.pdf",
      "primary_url_label": "PDF",
      "subject": "케이엠더블유",
      "subject_key": "케이엠더블유",
      "ticker": "032500",
      "views": 914,
      "analyst": null,
      "target_price": "70,000",
      "target_price_value": 70000,
      "opinion": "Buy",
      "opinion_normalized": "buy",
      "has_pdf_text": false,
      "content_sources": [
        "html"
      ],
      "excerpt": "12개월 목표가 70,000원으로 상향, 6월 오기 전에 매수하세요 KMW 주가에 있어 중요한 건 미국 통신사 CAPEX 전망 및 2027~2028년 추정 실적인데 미국에서 예상보다 양호한 규제 정책 및 통신사 CAPEX 전망이 발표되고 있기 때문이다.",
      "summary": "12개월 목표가 70,000원으로 상향, 6월 오기 전에 매수하세요 KMW 주가에 있어 중요한 건 미국 통신사 CAPEX 전망 및 2027~2028년 추정 실적인데 미국에서 예상보다 양호한 규제 정책 및 통신사 CAPEX 전망이 발표되고 있기 때문이다. 2026년 실적 전망치를 소폭 하향 조정하나 2027/2028년 실적 전망치는 이전 수준을 유지하며 최근 미국/국내 통신장비 업체들의 주가 상승을 감안하여 Target Multiple을 상향 조정하였다.",
      "summary_engine": "rule",
      "investment_memo": {},
      "score": 12.95,
      "score_reasons": [
        "종목분석 카테고리",
        "관심 종목(삼성전자)",
        "목표가 포함",
        "투자의견 포함",
        "우선 추적 증권사"
      ],
      "score_breakdown": [
        {
          "label": "관심 종목",
          "value": 4.0,
          "kind": "boost"
        },
        {
          "label": "종목분석 카테고리",
          "value": 3.2,
          "kind": "boost"
        },
        {
          "label": "조회수",
          "value": 2.3,
          "kind": "boost"
        },
        {
          "label": "우선 추적 증권사",
          "value": 0.9,
          "kind": "boost"
        },
        {
          "label": "제목 키워드: 실적",
          "value": 0.9,
          "kind": "boost"
        },
        {
          "label": "목표가",
          "value": 0.7,
          "kind": "boost"
        },
        {
          "label": "투자의견",
          "value": 0.6,
          "kind": "boost"
        },
        {
          "label": "본문 정보량",
          "value": 0.25,
          "kind": "boost"
        },
        {
          "label": "소스 가중치",
          "value": 0.1,
          "kind": "boost"
        }
      ],
      "link_health": {
        "status": "pdf_preferred",
        "primary_kind": "pdf",
        "has_pdf": true,
        "has_detail": true,
        "detail_host": "finance.naver.com",
        "pdf_host": "stock.pstatic.net",
        "note": "PDF 링크를 대표 링크로 사용합니다."
      },
      "priority_subject_matches": [
        "삼성전자"
      ],
      "priority_keyword_matches": [],
      "is_priority_match": true,
      "previous_report_date": null,
      "previous_target_price": null,
      "previous_opinion": null,
      "previous_analyst": null,
      "target_price_change": null,
      "target_price_change_pct": null,
      "opinion_changed": false,
      "opinion_change_direction": null,
      "analyst_changed": false,
      "coverage_initiated": true,
      "change_types": [
        "coverage_initiated"
      ],
      "change_reasons": [
        "신규 커버리지"
      ],
      "has_change_signal": true
    }
  ],
  "recent_changes": [
    {
      "source": "naver_research",
      "category": "company",
      "category_label": "종목분석",
      "report_id": "93145",
      "title": "중요한 건 올해가 아닌 내년도 실적입니다",
      "display_title": "케이엠더블유 - 중요한 건 올해가 아닌 내년도 실적입니다",
      "broker": "하나증권",
      "published_date": "2026-05-19",
      "detail_url": "https://finance.naver.com/research/company_read.naver?nid=93145&page=1",
      "pdf_url": "https://stock.pstatic.net/stock-research/company/57/20260519_company_123293000.pdf",
      "primary_url": "https://stock.pstatic.net/stock-research/company/57/20260519_company_123293000.pdf",
      "primary_url_label": "PDF",
      "subject": "케이엠더블유",
      "subject_key": "케이엠더블유",
      "ticker": "032500",
      "views": 914,
      "analyst": null,
      "target_price": "70,000",
      "target_price_value": 70000,
      "opinion": "Buy",
      "opinion_normalized": "buy",
      "has_pdf_text": false,
      "content_sources": [
        "html"
      ],
      "excerpt": "12개월 목표가 70,000원으로 상향, 6월 오기 전에 매수하세요 KMW 주가에 있어 중요한 건 미국 통신사 CAPEX 전망 및 2027~2028년 추정 실적인데 미국에서 예상보다 양호한 규제 정책 및 통신사 CAPEX 전망이 발표되고 있기 때문이다.",
      "summary": "12개월 목표가 70,000원으로 상향, 6월 오기 전에 매수하세요 KMW 주가에 있어 중요한 건 미국 통신사 CAPEX 전망 및 2027~2028년 추정 실적인데 미국에서 예상보다 양호한 규제 정책 및 통신사 CAPEX 전망이 발표되고 있기 때문이다. 2026년 실적 전망치를 소폭 하향 조정하나 2027/2028년 실적 전망치는 이전 수준을 유지하며 최근 미국/국내 통신장비 업체들의 주가 상승을 감안하여 Target Multiple을 상향 조정하였다.",
      "summary_engine": "rule",
      "investment_memo": {},
      "score": 12.95,
      "score_reasons": [
        "종목분석 카테고리",
        "관심 종목(삼성전자)",
        "목표가 포함",
        "투자의견 포함",
        "우선 추적 증권사"
      ],
      "score_breakdown": [
        {
          "label": "관심 종목",
          "value": 4.0,
          "kind": "boost"
        },
        {
          "label": "종목분석 카테고리",
          "value": 3.2,
          "kind": "boost"
        },
        {
          "label": "조회수",
          "value": 2.3,
          "kind": "boost"
        },
        {
          "label": "우선 추적 증권사",
          "value": 0.9,
          "kind": "boost"
        },
        {
          "label": "제목 키워드: 실적",
          "value": 0.9,
          "kind": "boost"
        },
        {
          "label": "목표가",
          "value": 0.7,
          "kind": "boost"
        },
        {
          "label": "투자의견",
          "value": 0.6,
          "kind": "boost"
        },
        {
          "label": "본문 정보량",
          "value": 0.25,
          "kind": "boost"
        },
        {
          "label": "소스 가중치",
          "value": 0.1,
          "kind": "boost"
        }
      ],
      "link_health": {
        "status": "pdf_preferred",
        "primary_kind": "pdf",
        "has_pdf": true,
        "has_detail": true,
        "detail_host": "finance.naver.com",
        "pdf_host": "stock.pstatic.net",
        "note": "PDF 링크를 대표 링크로 사용합니다."
      },
      "priority_subject_matches": [
        "삼성전자"
      ],
      "priority_keyword_matches": [],
      "is_priority_match": true,
      "previous_report_date": null,
      "previous_target_price": null,
      "previous_opinion": null,
      "previous_analyst": null,
      "target_price_change": null,
      "target_price_change_pct": null,
      "opinion_changed": false,
      "opinion_change_direction": null,
      "analyst_changed": false,
      "coverage_initiated": true,
      "change_types": [
        "coverage_initiated"
      ],
      "change_reasons": [
        "신규 커버리지"
      ],
      "has_change_signal": true
    }
  ],
  "timeline": [
    {
      "source": "naver_research",
      "category": "company",
      "category_label": "종목분석",
      "report_id": "93145",
      "title": "중요한 건 올해가 아닌 내년도 실적입니다",
      "display_title": "케이엠더블유 - 중요한 건 올해가 아닌 내년도 실적입니다",
      "broker": "하나증권",
      "published_date": "2026-05-19",
      "detail_url": "https://finance.naver.com/research/company_read.naver?nid=93145&page=1",
      "pdf_url": "https://stock.pstatic.net/stock-research/company/57/20260519_company_123293000.pdf",
      "primary_url": "https://stock.pstatic.net/stock-research/company/57/20260519_company_123293000.pdf",
      "primary_url_label": "PDF",
      "subject": "케이엠더블유",
      "subject_key": "케이엠더블유",
      "ticker": "032500",
      "views": 914,
      "analyst": null,
      "target_price": "70,000",
      "target_price_value": 70000,
      "opinion": "Buy",
      "opinion_normalized": "buy",
      "has_pdf_text": false,
      "content_sources": [
        "html"
      ],
      "excerpt": "12개월 목표가 70,000원으로 상향, 6월 오기 전에 매수하세요 KMW 주가에 있어 중요한 건 미국 통신사 CAPEX 전망 및 2027~2028년 추정 실적인데 미국에서 예상보다 양호한 규제 정책 및 통신사 CAPEX 전망이 발표되고 있기 때문이다.",
      "summary": "12개월 목표가 70,000원으로 상향, 6월 오기 전에 매수하세요 KMW 주가에 있어 중요한 건 미국 통신사 CAPEX 전망 및 2027~2028년 추정 실적인데 미국에서 예상보다 양호한 규제 정책 및 통신사 CAPEX 전망이 발표되고 있기 때문이다. 2026년 실적 전망치를 소폭 하향 조정하나 2027/2028년 실적 전망치는 이전 수준을 유지하며 최근 미국/국내 통신장비 업체들의 주가 상승을 감안하여 Target Multiple을 상향 조정하였다.",
      "summary_engine": "rule",
      "investment_memo": {},
      "score": 12.95,
      "score_reasons": [
        "종목분석 카테고리",
        "관심 종목(삼성전자)",
        "목표가 포함",
        "투자의견 포함",
        "우선 추적 증권사"
      ],
      "score_breakdown": [
        {
          "label": "관심 종목",
          "value": 4.0,
          "kind": "boost"
        },
        {
          "label": "종목분석 카테고리",
          "value": 3.2,
          "kind": "boost"
        },
        {
          "label": "조회수",
          "value": 2.3,
          "kind": "boost"
        },
        {
          "label": "우선 추적 증권사",
          "value": 0.9,
          "kind": "boost"
        },
        {
          "label": "제목 키워드: 실적",
          "value": 0.9,
          "kind": "boost"
        },
        {
          "label": "목표가",
          "value": 0.7,
          "kind": "boost"
        },
        {
          "label": "투자의견",
          "value": 0.6,
          "kind": "boost"
        },
        {
          "label": "본문 정보량",
          "value": 0.25,
          "kind": "boost"
        },
        {
          "label": "소스 가중치",
          "value": 0.1,
          "kind": "boost"
        }
      ],
      "link_health": {
        "status": "pdf_preferred",
        "primary_kind": "pdf",
        "has_pdf": true,
        "has_detail": true,
        "detail_host": "finance.naver.com",
        "pdf_host": "stock.pstatic.net",
        "note": "PDF 링크를 대표 링크로 사용합니다."
      },
      "priority_subject_matches": [
        "삼성전자"
      ],
      "priority_keyword_matches": [],
      "is_priority_match": true,
      "previous_report_date": null,
      "previous_target_price": null,
      "previous_opinion": null,
      "previous_analyst": null,
      "target_price_change": null,
      "target_price_change_pct": null,
      "opinion_changed": false,
      "opinion_change_direction": null,
      "analyst_changed": false,
      "coverage_initiated": true,
      "change_types": [
        "coverage_initiated"
      ],
      "change_reasons": [
        "신규 커버리지"
      ],
      "has_change_signal": true
    }
  ]
}