{
  "subject_key": "폰드그룹",
  "subject_name": "폰드그룹",
  "latest_report_date": "2026-05-06",
  "report_count": 1,
  "active_broker_count": 1,
  "active_brokers": [
    "유안타증권"
  ],
  "change_summary": {
    "changed_reports": 1,
    "target_price_up": 0,
    "target_price_down": 0,
    "opinion_changed": 0,
    "opinion_up": 0,
    "opinion_down": 0,
    "analyst_changed": 0,
    "coverage_initiated": 0,
    "estimate_signal_reports": 1,
    "earnings_estimate_up": 1,
    "earnings_estimate_down": 0,
    "margin_estimate_up": 0,
    "margin_estimate_down": 0
  },
  "target_summary": {
    "count": 0,
    "high": null,
    "low": null,
    "avg": null
  },
  "opinion_summary": [],
  "charts": {
    "target_price_history": [],
    "estimate_metric_history": [
      {
        "date": "2026-05-06",
        "broker": "유안타증권",
        "title": "폰드그룹 - 사업적 결합이 시작된다!",
        "ticker": null,
        "detail_url": "https://finance.naver.com/research/company_read.naver?nid=92476&page=1",
        "pdf_url": "https://stock.pstatic.net/stock-research/company/18/20260506_company_851237000.pdf",
        "primary_url": "https://stock.pstatic.net/stock-research/company/18/20260506_company_851237000.pdf",
        "target_price": null,
        "target_price_value": null,
        "opinion": null,
        "opinion_normalized": null,
        "score": 6.55,
        "has_change_signal": true,
        "estimate_signal_types": [
          "earnings_estimate_up"
        ],
        "estimate_reasons": [
          "이익 추정 상향/증가"
        ],
        "metric": "operating_profit",
        "metric_group": "earnings",
        "label": "영업이익",
        "period": null,
        "value": 171.9,
        "unit": "억원",
        "value_krw_100m": 171.9,
        "value_pct": null,
        "value_won": null,
        "change_pctp": null,
        "source_excerpt": "0억원, 영업이익 171.9억원으로 전년대비 각각 9."
      },
      {
        "date": "2026-05-06",
        "broker": "유안타증권",
        "title": "폰드그룹 - 사업적 결합이 시작된다!",
        "ticker": null,
        "detail_url": "https://finance.naver.com/research/company_read.naver?nid=92476&page=1",
        "pdf_url": "https://stock.pstatic.net/stock-research/company/18/20260506_company_851237000.pdf",
        "primary_url": "https://stock.pstatic.net/stock-research/company/18/20260506_company_851237000.pdf",
        "target_price": null,
        "target_price_value": null,
        "opinion": null,
        "opinion_normalized": null,
        "score": 6.55,
        "has_change_signal": true,
        "estimate_signal_types": [
          "earnings_estimate_up"
        ],
        "estimate_reasons": [
          "이익 추정 상향/증가"
        ],
        "metric": "revenue",
        "metric_group": "earnings",
        "label": "매출액",
        "period": null,
        "value": 1170.0,
        "unit": "억원",
        "value_krw_100m": 1170.0,
        "value_pct": null,
        "value_won": null,
        "change_pctp": null,
        "source_excerpt": "폰드그룹 - 사업적 결합이 시작된다! 사업적 결합이 시작된다! 폰드그룹 1Q26 Review 1Q26 실적은 매출액 1,170.0억원, 영업이익 171."
      }
    ],
    "opinion_distribution": [],
    "broker_timeline": [
      {
        "date": "2026-05-06",
        "broker": "유안타증권",
        "title": "폰드그룹 - 사업적 결합이 시작된다!",
        "ticker": null,
        "detail_url": "https://finance.naver.com/research/company_read.naver?nid=92476&page=1",
        "pdf_url": "https://stock.pstatic.net/stock-research/company/18/20260506_company_851237000.pdf",
        "primary_url": "https://stock.pstatic.net/stock-research/company/18/20260506_company_851237000.pdf",
        "target_price": null,
        "target_price_value": null,
        "opinion": null,
        "opinion_normalized": null,
        "score": 6.55,
        "has_change_signal": true,
        "estimate_signal_types": [
          "earnings_estimate_up"
        ],
        "estimate_reasons": [
          "이익 추정 상향/증가"
        ]
      }
    ],
    "window_days": 14
  },
  "target_price_history": [],
  "estimate_metric_history": [
    {
      "date": "2026-05-06",
      "broker": "유안타증권",
      "title": "폰드그룹 - 사업적 결합이 시작된다!",
      "ticker": null,
      "detail_url": "https://finance.naver.com/research/company_read.naver?nid=92476&page=1",
      "pdf_url": "https://stock.pstatic.net/stock-research/company/18/20260506_company_851237000.pdf",
      "primary_url": "https://stock.pstatic.net/stock-research/company/18/20260506_company_851237000.pdf",
      "target_price": null,
      "target_price_value": null,
      "opinion": null,
      "opinion_normalized": null,
      "score": 6.55,
      "has_change_signal": true,
      "estimate_signal_types": [
        "earnings_estimate_up"
      ],
      "estimate_reasons": [
        "이익 추정 상향/증가"
      ],
      "metric": "operating_profit",
      "metric_group": "earnings",
      "label": "영업이익",
      "period": null,
      "value": 171.9,
      "unit": "억원",
      "value_krw_100m": 171.9,
      "value_pct": null,
      "value_won": null,
      "change_pctp": null,
      "source_excerpt": "0억원, 영업이익 171.9억원으로 전년대비 각각 9."
    },
    {
      "date": "2026-05-06",
      "broker": "유안타증권",
      "title": "폰드그룹 - 사업적 결합이 시작된다!",
      "ticker": null,
      "detail_url": "https://finance.naver.com/research/company_read.naver?nid=92476&page=1",
      "pdf_url": "https://stock.pstatic.net/stock-research/company/18/20260506_company_851237000.pdf",
      "primary_url": "https://stock.pstatic.net/stock-research/company/18/20260506_company_851237000.pdf",
      "target_price": null,
      "target_price_value": null,
      "opinion": null,
      "opinion_normalized": null,
      "score": 6.55,
      "has_change_signal": true,
      "estimate_signal_types": [
        "earnings_estimate_up"
      ],
      "estimate_reasons": [
        "이익 추정 상향/증가"
      ],
      "metric": "revenue",
      "metric_group": "earnings",
      "label": "매출액",
      "period": null,
      "value": 1170.0,
      "unit": "억원",
      "value_krw_100m": 1170.0,
      "value_pct": null,
      "value_won": null,
      "change_pctp": null,
      "source_excerpt": "폰드그룹 - 사업적 결합이 시작된다! 사업적 결합이 시작된다! 폰드그룹 1Q26 Review 1Q26 실적은 매출액 1,170.0억원, 영업이익 171."
    }
  ],
  "opinion_distribution": [],
  "broker_timeline": [
    {
      "date": "2026-05-06",
      "broker": "유안타증권",
      "title": "폰드그룹 - 사업적 결합이 시작된다!",
      "ticker": null,
      "detail_url": "https://finance.naver.com/research/company_read.naver?nid=92476&page=1",
      "pdf_url": "https://stock.pstatic.net/stock-research/company/18/20260506_company_851237000.pdf",
      "primary_url": "https://stock.pstatic.net/stock-research/company/18/20260506_company_851237000.pdf",
      "target_price": null,
      "target_price_value": null,
      "opinion": null,
      "opinion_normalized": null,
      "score": 6.55,
      "has_change_signal": true,
      "estimate_signal_types": [
        "earnings_estimate_up"
      ],
      "estimate_reasons": [
        "이익 추정 상향/증가"
      ]
    }
  ],
  "broker_summary": [
    {
      "name": "유안타증권",
      "count": 1
    }
  ],
  "category_summary": [
    {
      "label": "종목분석",
      "count": 1
    }
  ],
  "latest_by_broker": [
    {
      "source": "naver_research",
      "category": "company",
      "category_label": "종목분석",
      "report_id": "92476",
      "title": "사업적 결합이 시작된다!",
      "display_title": "폰드그룹 - 사업적 결합이 시작된다!",
      "broker": "유안타증권",
      "published_date": "2026-05-06",
      "detail_url": "https://finance.naver.com/research/company_read.naver?nid=92476&page=1",
      "pdf_url": "https://stock.pstatic.net/stock-research/company/18/20260506_company_851237000.pdf",
      "subject": "폰드그룹",
      "subject_key": "폰드그룹",
      "views": 1112,
      "analyst": null,
      "target_price": null,
      "target_price_value": null,
      "opinion": null,
      "opinion_normalized": null,
      "has_pdf_text": false,
      "content_sources": [
        "html"
      ],
      "excerpt": "1Q26 Review 1Q26 실적은 매출액 1,170.0억원, 영업이익 171.9억원으로 전년대비 각각 9.9%, 19.1% 증가했다.",
      "summary": "1Q26 Review 1Q26 실적은 매출액 1,170.0억원, 영업이익 171.9억원으로 전년대비 각각 9.9%, 19.1% 증가했다. 계절성이 존재하는 산업특성상 전년대비로 비교하는 것이 합리적이다.",
      "summary_engine": "rule",
      "investment_memo": {},
      "score": 6.55,
      "score_reasons": [
        "종목분석 카테고리",
        "조회수 상위권",
        "우선 추적 증권사"
      ],
      "priority_subject_matches": [],
      "priority_keyword_matches": [],
      "is_priority_match": false,
      "previous_report_date": null,
      "previous_target_price": null,
      "previous_opinion": null,
      "previous_analyst": null,
      "target_price_change": null,
      "target_price_change_pct": null,
      "opinion_changed": false,
      "opinion_change_direction": null,
      "analyst_changed": false,
      "coverage_initiated": false,
      "change_types": [
        "earnings_estimate_up"
      ],
      "change_reasons": [
        "이익 추정 상향/증가"
      ],
      "has_change_signal": true,
      "ticker": null,
      "estimate_metrics": [
        {
          "metric": "revenue",
          "metric_group": "earnings",
          "label": "매출액",
          "period": null,
          "value": 1170.0,
          "unit": "억원",
          "source_excerpt": "폰드그룹 - 사업적 결합이 시작된다! 사업적 결합이 시작된다! 폰드그룹 1Q26 Review 1Q26 실적은 매출액 1,170.0억원, 영업이익 171.",
          "value_krw_100m": 1170.0
        },
        {
          "metric": "operating_profit",
          "metric_group": "earnings",
          "label": "영업이익",
          "period": null,
          "value": 171.9,
          "unit": "억원",
          "source_excerpt": "0억원, 영업이익 171.9억원으로 전년대비 각각 9.",
          "value_krw_100m": 171.9
        }
      ],
      "estimate_signal_types": [
        "earnings_estimate_up"
      ],
      "estimate_reasons": [
        "이익 추정 상향/증가"
      ]
    }
  ],
  "recent_changes": [
    {
      "source": "naver_research",
      "category": "company",
      "category_label": "종목분석",
      "report_id": "92476",
      "title": "사업적 결합이 시작된다!",
      "display_title": "폰드그룹 - 사업적 결합이 시작된다!",
      "broker": "유안타증권",
      "published_date": "2026-05-06",
      "detail_url": "https://finance.naver.com/research/company_read.naver?nid=92476&page=1",
      "pdf_url": "https://stock.pstatic.net/stock-research/company/18/20260506_company_851237000.pdf",
      "subject": "폰드그룹",
      "subject_key": "폰드그룹",
      "views": 1112,
      "analyst": null,
      "target_price": null,
      "target_price_value": null,
      "opinion": null,
      "opinion_normalized": null,
      "has_pdf_text": false,
      "content_sources": [
        "html"
      ],
      "excerpt": "1Q26 Review 1Q26 실적은 매출액 1,170.0억원, 영업이익 171.9억원으로 전년대비 각각 9.9%, 19.1% 증가했다.",
      "summary": "1Q26 Review 1Q26 실적은 매출액 1,170.0억원, 영업이익 171.9억원으로 전년대비 각각 9.9%, 19.1% 증가했다. 계절성이 존재하는 산업특성상 전년대비로 비교하는 것이 합리적이다.",
      "summary_engine": "rule",
      "investment_memo": {},
      "score": 6.55,
      "score_reasons": [
        "종목분석 카테고리",
        "조회수 상위권",
        "우선 추적 증권사"
      ],
      "priority_subject_matches": [],
      "priority_keyword_matches": [],
      "is_priority_match": false,
      "previous_report_date": null,
      "previous_target_price": null,
      "previous_opinion": null,
      "previous_analyst": null,
      "target_price_change": null,
      "target_price_change_pct": null,
      "opinion_changed": false,
      "opinion_change_direction": null,
      "analyst_changed": false,
      "coverage_initiated": false,
      "change_types": [
        "earnings_estimate_up"
      ],
      "change_reasons": [
        "이익 추정 상향/증가"
      ],
      "has_change_signal": true,
      "ticker": null,
      "estimate_metrics": [
        {
          "metric": "revenue",
          "metric_group": "earnings",
          "label": "매출액",
          "period": null,
          "value": 1170.0,
          "unit": "억원",
          "source_excerpt": "폰드그룹 - 사업적 결합이 시작된다! 사업적 결합이 시작된다! 폰드그룹 1Q26 Review 1Q26 실적은 매출액 1,170.0억원, 영업이익 171.",
          "value_krw_100m": 1170.0
        },
        {
          "metric": "operating_profit",
          "metric_group": "earnings",
          "label": "영업이익",
          "period": null,
          "value": 171.9,
          "unit": "억원",
          "source_excerpt": "0억원, 영업이익 171.9억원으로 전년대비 각각 9.",
          "value_krw_100m": 171.9
        }
      ],
      "estimate_signal_types": [
        "earnings_estimate_up"
      ],
      "estimate_reasons": [
        "이익 추정 상향/증가"
      ]
    }
  ],
  "timeline": [
    {
      "source": "naver_research",
      "category": "company",
      "category_label": "종목분석",
      "report_id": "92476",
      "title": "사업적 결합이 시작된다!",
      "display_title": "폰드그룹 - 사업적 결합이 시작된다!",
      "broker": "유안타증권",
      "published_date": "2026-05-06",
      "detail_url": "https://finance.naver.com/research/company_read.naver?nid=92476&page=1",
      "pdf_url": "https://stock.pstatic.net/stock-research/company/18/20260506_company_851237000.pdf",
      "subject": "폰드그룹",
      "subject_key": "폰드그룹",
      "views": 1112,
      "analyst": null,
      "target_price": null,
      "target_price_value": null,
      "opinion": null,
      "opinion_normalized": null,
      "has_pdf_text": false,
      "content_sources": [
        "html"
      ],
      "excerpt": "1Q26 Review 1Q26 실적은 매출액 1,170.0억원, 영업이익 171.9억원으로 전년대비 각각 9.9%, 19.1% 증가했다.",
      "summary": "1Q26 Review 1Q26 실적은 매출액 1,170.0억원, 영업이익 171.9억원으로 전년대비 각각 9.9%, 19.1% 증가했다. 계절성이 존재하는 산업특성상 전년대비로 비교하는 것이 합리적이다.",
      "summary_engine": "rule",
      "investment_memo": {},
      "score": 6.55,
      "score_reasons": [
        "종목분석 카테고리",
        "조회수 상위권",
        "우선 추적 증권사"
      ],
      "priority_subject_matches": [],
      "priority_keyword_matches": [],
      "is_priority_match": false,
      "previous_report_date": null,
      "previous_target_price": null,
      "previous_opinion": null,
      "previous_analyst": null,
      "target_price_change": null,
      "target_price_change_pct": null,
      "opinion_changed": false,
      "opinion_change_direction": null,
      "analyst_changed": false,
      "coverage_initiated": false,
      "change_types": [
        "earnings_estimate_up"
      ],
      "change_reasons": [
        "이익 추정 상향/증가"
      ],
      "has_change_signal": true,
      "ticker": null,
      "estimate_metrics": [
        {
          "metric": "revenue",
          "metric_group": "earnings",
          "label": "매출액",
          "period": null,
          "value": 1170.0,
          "unit": "억원",
          "source_excerpt": "폰드그룹 - 사업적 결합이 시작된다! 사업적 결합이 시작된다! 폰드그룹 1Q26 Review 1Q26 실적은 매출액 1,170.0억원, 영업이익 171.",
          "value_krw_100m": 1170.0
        },
        {
          "metric": "operating_profit",
          "metric_group": "earnings",
          "label": "영업이익",
          "period": null,
          "value": 171.9,
          "unit": "억원",
          "source_excerpt": "0억원, 영업이익 171.9억원으로 전년대비 각각 9.",
          "value_krw_100m": 171.9
        }
      ],
      "estimate_signal_types": [
        "earnings_estimate_up"
      ],
      "estimate_reasons": [
        "이익 추정 상향/증가"
      ]
    }
  ]
}